matched/__init__.py
matched/match.py
matched-2025.4.0.dist-info/METADATA
matched-2025.4.0.dist-info/WHEEL
matched-2025.4.0.dist-info/licenses/LICENSE
matched-2025.4.0.dist-info/RECORD
